isomer/__init__.py
isomer/hfos/__init__.py
isomer/hfos/core.py
hfos-1.3.0.dist-info/METADATA
hfos-1.3.0.dist-info/WHEEL
hfos-1.3.0.dist-info/entry_points.txt
hfos-1.3.0.dist-info/top_level.txt
hfos-1.3.0.dist-info/RECORD
